Workbook

Sheet Assumptions
H3: Assumptions
M4: Value
G5: Revenue Growth | M5: 0.042
G6: EBIT Margin | M6: 0.311
G7: Tax Rate | M7: 0.181
E8: CapEX % Revenue | M8: 0.028
F9: Depreciation % Revenue | M9: 0.029
G10: WACC | M10: 0.085
G11: Terminal Growth | M11: 0.025
H12: Shares Outstanding | M12: 14900
G13: Operating NWC(% Revenue) | M13: -0.081
G19: Notes
G20: NWC Calculation(2025)
G21: Operating Current Assets = Marketable Securities(18,763)+Accounts Receivable(39,777)+Vendor Receivables(33,180)+Inventory(5,718)+Other Current Assets(14,585) =$ 112,023
G22: Operating Current Liabilities = 69,860(Accounts Payable)+Other Current Liabilities(66,387)+Deffered Revenue(9,055) = $145,302
G23: 2025 NWC = -33,279
G24: NWC Calculation(2024)
G25: Operating Current Assets = 35,228+33,410+32,833+7,286+14,287=123,044
G26: Operating Current Liabilities = 68,960 + 78,304 + 8,249 = 155, 513
G27: =123044-155513 -> -32469
G29: 2024 | I29: Average
G30: =-32469/391035 -> -0.083033488 | I30: -0.0815
G31: 2025
G32: =33279/416161 -> 0.079966648
G34: Units in millions unless specified otherwise

Sheet Forecast
A1: Line item | B1: 2025A | C1: 2026E | D1: 2027E | E1: 2028E | F1: 2029E | G1: 2030E
A3: Revenue | B3: 416161 | C3: =B3*(1+Assumptions!$M$5) -> 433639.76 | D3: =C3*(1+Assumptions!$M$5) -> 451852.63 | E3: =D3*(1+Assumptions!$M$5) -> 470830.44 | F3: =E3*(1+Assumptions!$M$5) -> 490605.32 | G3: =F3*(1+Assumptions!$M$5) -> 511210.74
A5: EBIT | B5: 133050 | C5: =C3*Assumptions!$M$6 -> 134861.97 | D5: =D3*Assumptions!$M$6 -> 140526.17 | E5: =E3*Assumptions!$M$6 -> 146428.27 | F5: =F3*Assumptions!$M$6 -> 152578.25 | G5: =G3*Assumptions!$M$6 -> 158986.54
A7: Taxes | B7: 20719 | C7: =C5*Assumptions!$M$7 -> 24410.016 | D7: =D5*Assumptions!$M$7 -> 25435.237 | E7: =E5*Assumptions!$M$7 -> 26503.516 | F7: =F5*Assumptions!$M$7 -> 27616.664 | G7: =G5*Assumptions!$M$7 -> 28776.564
A9: NOPAT | B9: =(B5-B7) -> 112331 | C9: =C5-C7 -> 110451.95 | D9: =D5-D7 -> 115090.93 | E9: =E5-E7 -> 119924.75 | F9: =F5-F7 -> 124961.59 | G9: =G5-G7 -> 130209.98
A11: Depreciation | B11: 11698 | C11: =C3*Assumptions!$M$9 -> 12575.553 | D11: =D3*Assumptions!$M$9 -> 13103.726 | E11: =E3*Assumptions!$M$9 -> 13654.083 | F11: =F3*Assumptions!$M$9 -> 14227.554 | G11: =G3*Assumptions!$M$9 -> 14825.112
A13: CapEx | B13: 12715 | C13: =C3*Assumptions!$M$8 -> 12141.913 | D13: =D3*Assumptions!$M$8 -> 12651.874 | E13: =E3*Assumptions!$M$8 -> 13183.252 | F13: =F3*Assumptions!$M$8 -> 13736.949 | G13: =G3*Assumptions!$M$8 -> 14313.901
A15: Change in NWC | B15: 0 | C15: =(C3*Assumptions!$M$13)-(B3*Assumptions!$M$13) -> -1415.7797 | D15: =(D3*Assumptions!$M$13)-(C3*Assumptions!$M$13) -> -1475.2425 | E15: =(E3*Assumptions!$M$13)-(D3*Assumptions!$M$13) -> -1537.2027 | F15: =(F3*Assumptions!$M$13)-(E3*Assumptions!$M$13) -> -1601.7652 | G15: =(G3*Assumptions!$M$13)-(F3*Assumptions!$M$13) -> -1669.0393
A17: Free Cash Flow | B17: =B9+B11-B13-B15 -> 111314 | C17: =C9+C11-C13-C15 -> 112301.37 | D17: =D9+D11-D13-D15 -> 117018.03 | E17: =E9+E11-E13-E15 -> 121932.78 | F17: =F9+F11-F13-F15 -> 127053.96 | G17: =G9+G11-G13-G15 -> 132390.23

Sheet Discounted Cash Flow Valuation
B1: Discounted Cash Flow | J1: Enterprise Value Calculation | Q1: Implied Share Price
A2: Year | C2: FCF | D2: Discount Factor | E2: Present Value
J3: PV of Forecast FCF | L3: =E14 -> 478091.7 | Q3: Equity Value | R3: =L20 -> 2466855
A4: 2026E | C4: =Forecast!C17 -> 112301.37 | D4: =1/(1+Assumptions!M10)^1 -> 0.92165899 | E4: =C4*D4 -> 103503.57
J5: PV of Terminal Value | L5: =C26 -> 1504110.9 | Q5: Shares Outstanding | R5: =Assumptions!M12 -> 14900
A6: 2027E | C6: =Forecast!D17 -> 117018.03 | D6: =1/(1+Assumptions!M10)^2 -> 0.84945529 | E6: =C6*D6 -> 99401.582
J7: Enterprise Value | L7: =L3+L5 -> 1982202.6 | Q7: DCF Implied Share Price | R7: =R3/R5 -> 165.56074
A8: 2028E | C8: =Forecast!E17 -> 121932.78 | D8: =1/(1+Assumptions!M10)^3 -> 0.7829081 | E8: =C8*D8 -> 95462.164
A10: 2029E | C10: =Forecast!F17 -> 127053.96 | D10: =1/(1+Assumptions!M10)^4 -> 0.72157428 | E10: =C10*D10 -> 91678.871
A12: 2030E | C12: =Forecast!G17 -> 132390.23 | D12: =1/(1+Assumptions!M10)^5 -> 0.66504542 | E12: =C12*D12 -> 88045.515
B14: PV of Forecast Period | E14: =SUM(E4:E12) -> 478091.7
A16: Terminal Value | J16: Equity Value Bridge
A18: Final Year FCF | C18: 172129 | J18: Enterprise Value | L18: =L7 -> 1982202.6
A20: Terminal Growth Rate | C20: 0.025 | J20: Equity Value | L20: 2466855
L21: (Enterprise Value + Cash & Investments - debt)
A22: WACC | C22: 0.085
A24: Terminal Value | C24: =(Forecast!G17*(1+'Discounted Cash Flow Valuation'!C20))/('Discounted Cash Flow Valuation'!C22-'Discounted Cash Flow Valuation'!C20) -> 2261666.4
A26: PV of Terminal Value | C26: =C24/(1+C22)^5 -> 1504110.9

Sheet Sensitivity Analysis
A1: Base Case Assumptions
A2: WACC | B2: 0.085
A3: Terminal Growth | B3: 0.025
A5: Valuation Conclusion | K5: Valuation Interpretation
A6: DCF Implied Share Price | D6: 165.56 | K6: The Discounted Cash Flow Model(DCF) estimates the value of the stock at around $165.56, based on a 8.5% WACC and 2.5% terminal growth rate. However, in accordance with todays share price of $333.52 there is a -51% downside. This implies that the stock is very overpriced due to 2026's aggressive expansion and structural margin changes. The valuation is heavily influenced by Apple's ability to generate consistent free cash flow gains, maintain strong operating margins. The EBIT margin of 31.1% and 4.2% revenue growth rate prove Apple's industry leader stance. In accordance with the heavy gap in the valuation, investors are assigning additional value to Apple based on its ecosystem strength, artificial intelligence stance, and several other key factors like market position. Apple additonally seems to be heavily reliant on the discount rate and terminal growth assumptions, the implied stock price changing heavily with a lower WACC and higher terminal growth rate.
A8: Current Share Price | D8: 335.52
A10: Upside/(Downside) | D10: =(D6-D8)/D8 -> -0.50655699
A12: DCF Sensitivity Analysis
A14: EV/Shares Outstanding = $165.56
B15: Terminal Growth
A16: WACC | B16: 0.02 | C16: 0.025 | D16: 0.03
A17: 0.075 | B17: 149.13 | C17: 161.23 | D17: 176.01
A18: 0.085 | B18: 127.08 | C18: 165.56 | D18: 144.88
A19: 0.095 | B19: 111.11 | C19: 117 | D19: 123.79

Sheet Investment Summary
A1: Company Overview | I1: Final Recommendation
A2: Apple Inc.(AAPL) is a global technology company that designs, manufactures, and sells consumer electronics, software, and Services. The company's main revenue stream is through iPhones and its Services segment
J3: Based on the DCF analysis, Apple appears to be overvalued in the current market. However, Apple continues to be a very strong pick due to its strong financial position, ability for long-term growth, ecosystem advantages, and positioning in the current market. Investors should consider if its positioning in artificial intelligence, Services, and innovation justifies the heavy market premium it trades under.
A6: Investment Thesis
A7: Strengths
A8: Strong Free Cash Flow Generation | B8: Apple consistently produces significant operating cash flow, supporting areas like investments and share repurchases
A10: High Profitability | B10: Strong operating margins and ecosystem positioning allow Apple to maintain its high profitability
A13: Services Growth | B13: Services segment provides recurring revenue and higher margins compared to hardware products
A16: Capital Return Program | B16: Continued Share Repurchases reduce shares outstanding and support earnings per share growth
A18: Risks
A20: International Trade | B20: A significant portion of their cash flow comes from unstable international trade economies
A23: Competition | B23: Apple trades in a significantly wide market and failure to stay competitive and innovate could lead to drops in margins
A26: Regulatory Risks | B26: Similar to international trade, regulations in the app store for certain countries may impact Apple's business model

Sheet References
I4: References
I6: Apple Inc. Annual Reports(Form 10-K)
I7: Apple Inc.(2025) Annual Report(Form 10-K)
I9: Apple Investor Relations - Financial Information
I10: Apple Inc. Financial Statements, SEC filings, and investor information
I12: U.S. Securities and Exchange Comission(SEC)
I13: Apple Inc. Form 10-K filings and company financial disclosures
I16: Yahoo Finance
I17: Apple Inc.(AAPL) historical and current market price information
